README.txt
setup.py
docs/INSTALL.txt
docs/LICENSE.GPL
docs/LICENSE.txt
snd/__init__.py
snd.PloneMemberChannel.egg-info/PKG-INFO
snd.PloneMemberChannel.egg-info/SOURCES.txt
snd.PloneMemberChannel.egg-info/dependency_links.txt
snd.PloneMemberChannel.egg-info/entry_points.txt
snd.PloneMemberChannel.egg-info/namespace_packages.txt
snd.PloneMemberChannel.egg-info/not-zip-safe
snd.PloneMemberChannel.egg-info/requires.txt
snd.PloneMemberChannel.egg-info/top_level.txt
snd/PloneMemberChannel/HISTORY.txt
snd/PloneMemberChannel/__init__.py
snd/PloneMemberChannel/channel.py
snd/PloneMemberChannel/configure.zcml
snd/PloneMemberChannel/form.py
snd/PloneMemberChannel/i18n.py
snd/PloneMemberChannel/patch.py
snd/PloneMemberChannel/rebuild_i18n.sh
snd/PloneMemberChannel/subscriptions.py
snd/PloneMemberChannel/tests.py
snd/PloneMemberChannel/vocab.py
snd/PloneMemberChannel/locales/snd.PloneMemberChannel.pot
snd/PloneMemberChannel/locales/en/LC_MESSAGES/snd.PloneMemberChannel.po
snd/PloneMemberChannel/locales/nl/LC_MESSAGES/snd.PloneMemberChannel.po