Metadata-Version: 1.0
Name: snd.PloneMemberChannel
Version: 1.3
Summary: Patch for Singing and Dancing that allows sending mails to plone members too.
Home-page: http://svn.plone.org/svn/plone/plone.example
Author: Zest software
Author-email: v.pretre@zestsoftware.nl
License: GPL
Keywords: singing dancing channel
Platform: UNKNOWN
Classifier: Framework :: Plone
Classifier: Programming Language :: Python
Classifier: Topic :: Software Development :: Libraries :: Python Modules
